tracking_markers/__init__.py
tracking_markers/tracking_points.py
tracking_markers/utils.py
tracking_markers-0.9.0.dist-info/LICENSE
tracking_markers-0.9.0.dist-info/METADATA
tracking_markers-0.9.0.dist-info/WHEEL
tracking_markers-0.9.0.dist-info/entry_points.txt
tracking_markers-0.9.0.dist-info/RECORD
