Metadata-Version: 2.3
Name: tracking-markers
Version: 0.9.0
Summary: A humble image tracking code
License: MIT
Keywords: image-tracking,opencv
Author: Giovanni Bordiga
Author-email: gbordiga@seas.harvard.edu
Requires-Python: >=3.9,<3.13
Classifier: License :: OSI Approved :: MIT License
Classifier: Programming Language :: Python :: 3
Classifier: Programming Language :: Python :: 3.9
Classifier: Programming Language :: Python :: 3.10
Classifier: Programming Language :: Python :: 3.11
Classifier: Programming Language :: Python :: 3.12
Requires-Dist: numpy (>=1.26.1,<2.0.0)
Requires-Dist: opencv-python (>=4.8.1.78,<5.0.0.0)
Requires-Dist: tqdm (>=4.67.1,<5.0.0)
Project-URL: Homepage, https://github.com/bertoldi-collab/tracking-markers
Project-URL: Repository, https://github.com/bertoldi-collab/tracking-markers
